copyutil.cpython-314t-x86_64-linux-musl.so
cqlsh/__init__.py
cqlsh/__main__.py
cqlsh/cqlsh.py
cqlshlib/__init__.py
cqlshlib/_version.py
cqlshlib/authproviderhandling.py
cqlshlib/copyutil.py
cqlshlib/cql3handling.py
cqlshlib/cqlhandling.py
cqlshlib/cqlshhandling.py
cqlshlib/displaying.py
cqlshlib/formatting.py
cqlshlib/helptopics.py
cqlshlib/pylexotron.py
cqlshlib/saferscanner.py
cqlshlib/sslhandling.py
cqlshlib/tracing.py
cqlshlib/util.py
cqlshlib/wcwidth.py
scylla_cqlsh-6.0.33.dist-info/METADATA
scylla_cqlsh-6.0.33.dist-info/WHEEL
scylla_cqlsh-6.0.33.dist-info/entry_points.txt
scylla_cqlsh-6.0.33.dist-info/top_level.txt
scylla_cqlsh-6.0.33.dist-info/RECORD
scylla_cqlsh-6.0.33.dist-info/licenses/LICENSE.txt
