Metadata-Version: 2.4
Name: scylla-cqlsh
Version: 6.0.33
Summary: cqlsh is a Python-based command-line client for running CQL commands on a scylla cluster.
Home-page: https://github.com/scylladb/scylla-cqlsh
Author: Israel Fruchter
Author-email: fruch@scylladb.com
License: Apache
Project-URL: Changelog, https://github.com/scylladb/scylla-cqlsh#changelog
Project-URL: Documentation, https://cassandra.apache.org/doc/latest/tools/cqlsh.html
Keywords: cql,scylladb,cassandra,cqlsh
Classifier: Development Status :: 5 - Production/Stable
Classifier: Environment :: Console
Classifier: Topic :: Database :: Front-Ends
Classifier: License :: OSI Approved :: Apache Software License
Classifier: Programming Language :: Python :: 3
Requires-Python: >=3.6
License-File: LICENSE.txt
Requires-Dist: scylla-driver>=3.25.10
Requires-Dist: lz4
Dynamic: classifier
Dynamic: license
Dynamic: license-file
Dynamic: requires-dist
